.gitignore
AToM-logo.png
LICENSE
MANIFEST.in
README.md
pyproject.toml
.github/workflows/publish.yml
.github/workflows/test.yml
.github/workflows/workflow.yml
atom_openmm/__init__.py
atom_openmm/abfe_explicit.py
atom_openmm/abfe_production.py
atom_openmm/abfe_structprep.py
atom_openmm/async_re.py
atom_openmm/gibbs_sampling.py
atom_openmm/local_openmm_transport.py
atom_openmm/make_atm_system_from_amber.py
atom_openmm/make_atm_system_from_pdb.py
atom_openmm/make_atm_system_from_rcpt_lig.py
atom_openmm/ommreplica.py
atom_openmm/ommsystem.py
atom_openmm/ommworker.py
atom_openmm/openmm_async_re.py
atom_openmm/rbfe_explicit.py
atom_openmm/rbfe_production.py
atom_openmm/rbfe_structprep.py
atom_openmm/temperatureRE_explicit.py
atom_openmm/transport.py
atom_openmm/uwham.py
atom_openmm/utils/AtomUtils.py
atom_openmm/utils/__init__.py
atom_openmm/utils/config.py
atom_openmm/utils/logging.conf
atom_openmm/utils/singal_guard.py
atom_openmm/utils/timer.py
atom_openmm_unofficial.egg-info/PKG-INFO
atom_openmm_unofficial.egg-info/SOURCES.txt
atom_openmm_unofficial.egg-info/dependency_links.txt
atom_openmm_unofficial.egg-info/entry_points.txt
atom_openmm_unofficial.egg-info/requires.txt
atom_openmm_unofficial.egg-info/top_level.txt
examples/README.md
examples/ABFE/fkbp/README.md
examples/ABFE/fkbp/ligands/but.sdf
examples/ABFE/fkbp/ligands/dap.sdf
examples/ABFE/fkbp/ligands/dapp.sdf
examples/ABFE/fkbp/ligands/dmso.sdf
examples/ABFE/fkbp/ligands/dss.sdf
examples/ABFE/fkbp/ligands/prp.sdf
examples/ABFE/fkbp/ligands/thi.sdf
examples/ABFE/fkbp/receptor/fkbp.pdb
examples/ABFE/fkbp/scripts/analyze.sh
examples/ABFE/fkbp/scripts/asyncre_template.cntl
examples/ABFE/fkbp/scripts/create_cntlfile_from_template_abfe.py
examples/ABFE/fkbp/scripts/free_energies_template.sh
examples/ABFE/fkbp/scripts/prep_template.sh
examples/ABFE/fkbp/scripts/run_template.sh
examples/ABFE/fkbp/scripts/setup-atm.sh
examples/ABFE/fkbp/scripts/setup-settings.sh
examples/ABFE/fkbp/scripts/uwham_analysis.R
examples/ABFE/temoa-g1/README.md
examples/ABFE/temoa-g1/analyze.sh
examples/ABFE/temoa-g1/nodefile
examples/ABFE/temoa-g1/temoa-g1.inpcrd
examples/ABFE/temoa-g1/temoa-g1.prmtop
examples/ABFE/temoa-g1/temoa-g1_asyncre.cntl
examples/ABFE/temoa-g1/uwham_analysis.R
examples/RBFE/cdk2/README.md
