Metadata-Version: 2.4
Name: atom-openmm-unofficial
Version: 8.2.4
Summary: Asynchronous Replica Exchange with OpenMM
Author-email: Emilio Gallicchio <emilio.gallicchio@gmail.com>
Project-URL: Homepage, https://github.com/Gallicchio-Lab/AToM-OpenMM
Project-URL: Bug Tracker, https://github.com/Gallicchio-Lab/AToM-OpenMM/issues
Classifier: Programming Language :: Python :: 3
Classifier: Operating System :: POSIX :: Linux
Requires-Python: >=3.8
License-File: LICENSE
Requires-Dist: configobj
Requires-Dist: numpy
Requires-Dist: six
Dynamic: license-file
